blockly_executor/__init__.py
blockly_executor/__version__.py
blockly_executor/block.py
blockly_executor/context.py
blockly_executor/context_file.py
blockly_executor/context_memory.py
blockly_executor/context_props.py
blockly_executor/exceptions.py
blockly_executor/executor.py
blockly_executor/workspace.py
blockly_executor/workspace_gluer.py
blockly_executor/workspace_gluer_json.py
blockly_executor/workspace_gluer_xml.py
blockly_executor/workspace_json.py
blockly_executor/workspace_xml.py
blockly_executor/block_templates/__init__.py
blockly_executor/block_templates/multi_thread_loop.py
blockly_executor/block_templates/paging_loop.py
blockly_executor/block_templates/simple_block.py
blockly_executor/blocks/__init__.py
blockly_executor/blocks/controls_for.py
blockly_executor/blocks/controls_foreach.py
blockly_executor/blocks/controls_if.py
blockly_executor/blocks/controls_repeat_ext.py
blockly_executor/blocks/lists_create_with.py
blockly_executor/blocks/lists_get_index.py
blockly_executor/blocks/lists_length.py
blockly_executor/blocks/lists_set_index.py
blockly_executor/blocks/logic_boolean.py
blockly_executor/blocks/logic_compare.py
blockly_executor/blocks/logic_operation.py
blockly_executor/blocks/math_arithmetic.py
blockly_executor/blocks/math_number.py
blockly_executor/blocks/procedures_callnoreturn.py
blockly_executor/blocks/procedures_callreturn.py
blockly_executor/blocks/procedures_defnoreturn.py
blockly_executor/blocks/procedures_defreturn.py
blockly_executor/blocks/procedures_ifreturn.py
blockly_executor/blocks/root.py
blockly_executor/blocks/text.py
blockly_executor/blocks/text_join.py
blockly_executor/blocks/variables_get.py
blockly_executor/blocks/variables_set.py
blockly_executor/helpers/__init__.py
blockly_executor/helpers/compare_objects.py
blockly_executor/helpers/data_getters_setter.py
blockly_executor/helpers/sap_xml_serializer.py
blockly_executor/helpers/xdto_serializer.py
blockly_executor/helpers/xml_serializer.py
blockly_executor-2.0.0.dist-info/LICENSE
blockly_executor-2.0.0.dist-info/METADATA
blockly_executor-2.0.0.dist-info/WHEEL
blockly_executor-2.0.0.dist-info/top_level.txt
blockly_executor-2.0.0.dist-info/RECORD
