Metadata-Version: 2.1
Name: blockly_executor
Version: 2.0.0
Summary: blockly xml interpreter and debugger
Home-page: https://gitlab.com/razgovorov/blockly_executor
Author: Razgovorov Mikhail
Author-email: 1338833@gmail.com
License: MIT
Keywords: blockly
Classifier: Development Status :: 4 - Beta
Classifier: Natural Language :: Russian
Classifier: License :: OSI Approved :: MIT License
Classifier: Programming Language :: Python :: 3
Classifier: Topic :: Software Development
Classifier: Operating System :: OS Independent
Requires-Python: >=3.9
License-File: LICENSE
Requires-Dist: Bubot_Helpers>=4.0.0
